pytafseer/__init__.py
pytafseer/settings.py
pytafseer-0.1.1.dist-info/AUTHORS.rst
pytafseer-0.1.1.dist-info/LICENSE
pytafseer-0.1.1.dist-info/METADATA
pytafseer-0.1.1.dist-info/WHEEL
pytafseer-0.1.1.dist-info/top_level.txt
pytafseer-0.1.1.dist-info/RECORD
