Metadata-Version: 2.1
Name: pytafseer
Version: 0.1.1
Summary: Python Package (wrapper) for Quran Tafseer REST APIs
Home-page: https://github.com/Quran-Tafseer/pytafseer/
Author: Emad Mokhtar
Author-email: emad.m.habib@gmail.com
License: MIT license
Keywords: tafseer,quran,translation,tafsir
Platform: UNKNOWN
Classifier: Development Status :: 2 - Pre-Alpha
Classifier: Intended Audience :: Developers
Classifier: License :: OSI Approved :: MIT License
Classifier: Natural Language :: English
Classifier: Programming Language :: Python :: 3
Classifier: Programming Language :: Python :: 3.4
Classifier: Programming Language :: Python :: 3.5
Classifier: Programming Language :: Python :: 3.6
Classifier: Programming Language :: Python :: 3.7
Requires-Dist: requests
